{"name":"Search with AVIVA keyword on google home page and invalid login on AVIVA login page","id":"google-search-functionality;search-with-aviva-keyword-on-google-home-page-and-invalid-login-on-aviva-login-page","testSteps":[{"number":1,"description":"Search with AVIVA keyword on google home page and invalid login on AVIVA login page #1: {keyword1\u003dAVIVA, message\u003dPlease fill in all 3 fields.}","duration":21281,"startTime":"2018-06-28T17:02:09.124+05:30[Asia/Calcutta]","screenshots":[{"screenshot":"9f3860cf503139fbcf71bb2f517898fea820e335108c7feb2fdd803551fda640.png"}],"result":"SUCCESS","precondition":false,"children":[{"number":2,"description":"Given launch the google home page","duration":9031,"startTime":"2018-06-28T17:02:09.124+05:30[Asia/Calcutta]","screenshots":[{"screenshot":"6b4b7ac7a454666653e3a99312b1397ad9220d425becd8b0d86ba63018026327.png"}],"result":"SUCCESS","precondition":false,"children":[{"number":3,"description":"Open google search","duration":8771,"startTime":"2018-06-28T17:02:09.129+05:30[Asia/Calcutta]","screenshots":[{"screenshot":"e265450e68c42eeef186ef6e73aa823ea30c12b565e65db908f9acf254c30de8.png"}],"result":"SUCCESS","precondition":false}]},{"number":4,"description":"And search with the string \"AVIVA\"","duration":1143,"startTime":"2018-06-28T17:02:18.156+05:30[Asia/Calcutta]","screenshots":[{"screenshot":"6b4b7ac7a454666653e3a99312b1397ad9220d425becd8b0d86ba63018026327.png"},{"screenshot":"6b88ee9f6457fbf208a4ca2f101c58aea0d79d8bba44c07f42f26dd97dccc9a9.png"}],"result":"SUCCESS","precondition":false,"children":[{"number":5,"description":"Search keyword: AVIVA","duration":664,"startTime":"2018-06-28T17:02:18.399+05:30[Asia/Calcutta]","screenshots":[{"screenshot":"e265450e68c42eeef186ef6e73aa823ea30c12b565e65db908f9acf254c30de8.png"},{"screenshot":"6b88ee9f6457fbf208a4ca2f101c58aea0d79d8bba44c07f42f26dd97dccc9a9.png"}],"result":"SUCCESS","precondition":false}]},{"number":6,"description":"When click on search button","duration":4592,"startTime":"2018-06-28T17:02:19.300+05:30[Asia/Calcutta]","screenshots":[{"screenshot":"a6f70a1606ea9f29e5880d77a927dc81cb99bd4f1f9402e37e76802a8511ec77.png"},{"screenshot":"26e6e1e5842b711319ac47ae366a4218037dc45c7010b1166eb75e46d9a43339.png"}],"result":"SUCCESS","precondition":false,"children":[{"number":7,"description":"Click search","duration":4084,"startTime":"2018-06-28T17:02:19.536+05:30[Asia/Calcutta]","screenshots":[{"screenshot":"a6f70a1606ea9f29e5880d77a927dc81cb99bd4f1f9402e37e76802a8511ec77.png"},{"screenshot":"26e6e1e5842b711319ac47ae366a4218037dc45c7010b1166eb75e46d9a43339.png"}],"result":"SUCCESS","precondition":false}]},{"number":8,"description":"Then I click on Aviva link and login button without providing credentials","duration":4906,"startTime":"2018-06-28T17:02:23.893+05:30[Asia/Calcutta]","screenshots":[{"screenshot":"26e6e1e5842b711319ac47ae366a4218037dc45c7010b1166eb75e46d9a43339.png"},{"screenshot":"b85cad4e3695517ba098d49e7baffbcf1f6da28b8263ed7668b8ecc9690cc3f1.png"}],"result":"SUCCESS","precondition":false,"children":[{"number":9,"description":"Invalid aviva login","duration":4322,"startTime":"2018-06-28T17:02:24.168+05:30[Asia/Calcutta]","screenshots":[{"screenshot":"26e6e1e5842b711319ac47ae366a4218037dc45c7010b1166eb75e46d9a43339.png"},{"screenshot":"965c022e266fa3de2e7024421bbe7716f8b3c7672906ae492f1818d925195176.png"}],"result":"SUCCESS","precondition":false}]},{"number":10,"description":"And the result should be the error \"Please fill in all 3 fields.\" display","duration":1289,"startTime":"2018-06-28T17:02:28.799+05:30[Asia/Calcutta]","screenshots":[{"screenshot":"eccaf653e23de891cd6f6c6076c8fd8e0a05b33bcaebaef2fb441cefd8b18341.png"},{"screenshot":"679351861e4430dfb8382d87f34cbbfaf84452c309c69b62922977c2f3fc7c70.png"}],"result":"SUCCESS","precondition":false,"children":[{"number":11,"description":"Verify error message: Please fill in all 3 fields.","duration":657,"startTime":"2018-06-28T17:02:29.098+05:30[Asia/Calcutta]","screenshots":[{"screenshot":"b4ea45346624238cdd0670dc37af922f0873ddb42d6970ee7ace827dd305d121.png"},{"screenshot":"6862e2959e007340b31200f183fb2321bba07549f19c1d21f6a14bc63adbedd9.png"}],"result":"SUCCESS","precondition":false}]}]}],"userStory":{"id":"google-search-functionality","storyName":"Google search functionality","path":"src/test/resources/features/consult_dictionary/AvivaScenarios.feature","narrative":"  Open the google page and search with keyword AVIVA\n  verify the number of links returned and\n  print the 5th link text.","type":"feature"},"featureTag":{"name":"Consult dictionary/Google search functionality","type":"feature"},"title":"Search with AVIVA keyword on google home page and invalid login on AVIVA login page","backgroundTitle":"","backgroundDescription":"","tags":[{"name":"NegativeScenario","type":"tag"},{"name":"Consult dictionary","type":"capability"},{"name":"Consult dictionary/Google search functionality","type":"feature"}],"startTime":"2018-06-28T17:02:09.122+05:30[Asia/Calcutta]","duration":21568,"projectKey":"","sessionId":"ba38a780a7d4526157dad0188bcde1bf","driver":"chrome","dataTable":{"headers":["keyword1","message"],"rows":[{"values":["AVIVA","Please fill in all 3 fields."],"result":"SUCCESS"}],"predefinedRows":true,"scenarioOutline":"And search with the string \"\u003ckeyword1\u003e\"\n\rWhen click on search button\n\rThen I click on Aviva link and login button without providing credentials\n\rAnd the result should be the error \"\u003cmessage\u003e\" display\n\r","dataSetDescriptors":[{"startRow":0,"rowCount":0,"name":""}]},"manual":false,"testSource":"Cucumber","result":"SUCCESS"}